eva_tools/__init__.py
eva_tools/merge_eva.py
eva_tools/plot_eva.py
eva_tools/read_eva.py
eva_tools/write_eva.py
eva_tools-1.0.0.dist-info/LICENSE
eva_tools-1.0.0.dist-info/METADATA
eva_tools-1.0.0.dist-info/WHEEL
eva_tools-1.0.0.dist-info/top_level.txt
eva_tools-1.0.0.dist-info/RECORD
